dnaio/__init__.py
dnaio/_bam.py
dnaio/_conversions.h
dnaio/_core.cpython-314t-x86_64-linux-gnu.so
dnaio/_core.pyi
dnaio/_util.py
dnaio/_version.py
dnaio/_version.pyi
dnaio/ascii_check.h
dnaio/bam.h
dnaio/chunks.py
dnaio/exceptions.py
dnaio/interfaces.py
dnaio/multipleend.py
dnaio/pairedend.py
dnaio/py.typed
dnaio/readers.py
dnaio/singleend.py
dnaio/writers.py
dnaio-1.2.4.dist-info/METADATA
dnaio-1.2.4.dist-info/WHEEL
dnaio-1.2.4.dist-info/top_level.txt
dnaio-1.2.4.dist-info/RECORD
dnaio-1.2.4.dist-info/licenses/LICENSE
