Metadata-Version: 2.4
Name: dnaio
Version: 1.2.4
Summary: Read and write FASTA and FASTQ files efficiently
Author-email: Marcel Martin <marcel.martin@scilifelab.se>, Ruben Vorderman <r.h.p.vorderman@lumc.nl>
License-Expression: MIT
Project-URL: Homepage, https://dnaio.readthedocs.io/
Project-URL: Changelog, https://dnaio.readthedocs.io/en/latest/changes.html
Project-URL: Repository, https://github.com/marcelm/dnaio/
Classifier: Development Status :: 5 - Production/Stable
Classifier: Intended Audience :: Science/Research
Classifier: Programming Language :: Cython
Classifier: Programming Language :: Python :: 3
Classifier: Topic :: Scientific/Engineering :: Bio-Informatics
Requires-Python: >=3.10
License-File: LICENSE
Requires-Dist: xopen>=1.4.0
Provides-Extra: dev
Requires-Dist: Cython; extra == "dev"
Requires-Dist: pytest; extra == "dev"
Dynamic: license-file
